{
  "initials": [
    { "id": "b", "pinyin": "b", "ipa": "/p/", "description": "unaspirated p, like 's**p**in'" },
    { "id": "p", "pinyin": "p", "ipa": "/pʰ/", "description": "aspirated p, like '**p**in'" },
    { "id": "m", "pinyin": "m", "ipa": "/m/", "description": "like '**m**an'" },
    { "id": "f", "pinyin": "f", "ipa": "/f/", "description": "like '**f**an'" },
    { "id": "d", "pinyin": "d", "ipa": "/t/", "description": "unaspirated t, like 's**t**op'" },
    { "id": "t", "pinyin": "t", "ipa": "/tʰ/", "description": "aspirated t, like '**t**op'" },
    { "id": "n", "pinyin": "n", "ipa": "/n/", "description": "like '**n**o'" },
    { "id": "l", "pinyin": "l", "ipa": "/l/", "description": "like '**l**ow'" },
    { "id": "g", "pinyin": "g", "ipa": "/k/", "description": "unaspirated k, like 's**k**ip'" },
    { "id": "k", "pinyin": "k", "ipa": "/kʰ/", "description": "aspirated k, like '**k**ey'" },
    { "id": "h", "pinyin": "h", "ipa": "/x/", "description": "like English '**h**ay' but rougher" },
    {
      "id": "j",
      "pinyin": "j",
      "ipa": "/tɕ/",
      "description": "unaspirated ch, like '**j**eep' with tongue up"
    },
    {
      "id": "q",
      "pinyin": "q",
      "ipa": "/tɕʰ/",
      "description": "aspirated ch, like '**ch**eek' with tongue up"
    },
    {
      "id": "x",
      "pinyin": "x",
      "ipa": "/ɕ/",
      "description": "like '**sh**e' with a smile and tongue up"
    },
    {
      "id": "zh",
      "pinyin": "zh",
      "ipa": "/ʈʂ/",
      "description": "unaspirated j, like '**j**aw' with curled tongue"
    },
    {
      "id": "ch",
      "pinyin": "ch",
      "ipa": "/ʈʂʰ/",
      "description": "aspirated ch, like '**ch**urch' with curled tongue"
    },
    {
      "id": "sh",
      "pinyin": "sh",
      "ipa": "/ʂ/",
      "description": "like '**sh**ip' with curled tongue"
    },
    {
      "id": "r",
      "pinyin": "r",
      "ipa": "/ʐ/",
      "description": "like '**r**eef' but with curled tongue"
    },
    { "id": "z", "pinyin": "z", "ipa": "/ts/", "description": "unaspirated ts, like 'ca**ts**'" },
    {
      "id": "c",
      "pinyin": "c",
      "ipa": "/tsʰ/",
      "description": "aspirated ts, like 'ca**ts**' with a puff of air"
    },
    { "id": "s", "pinyin": "s", "ipa": "/s/", "description": "like '**s**up'" }
  ],
  "finals": [
    { "id": "a", "pinyin": "a", "type": "simple", "description": "like '**a**h'" },
    { "id": "o", "pinyin": "o", "type": "simple", "description": "like '**o**h'" },
    { "id": "e", "pinyin": "e", "type": "simple", "description": "like '**u**h'" },
    { "id": "i", "pinyin": "i", "type": "simple", "description": "like '**ea**t'" },
    { "id": "u", "pinyin": "u", "type": "simple", "description": "like '**oo**ze'" },
    { "id": "ü", "pinyin": "ü", "type": "simple", "description": "pursed lips 'ee' sound" },
    { "id": "ai", "pinyin": "ai", "type": "compound", "description": "like '**eye**'" },
    { "id": "ei", "pinyin": "ei", "type": "compound", "description": "like '**ay**'" },
    { "id": "ao", "pinyin": "ao", "type": "compound", "description": "like '**ow**' in 'n**ow**'" },
    { "id": "ou", "pinyin": "ou", "type": "compound", "description": "like '**oh**'" },
    { "id": "ia", "pinyin": "ia", "type": "compound", "description": "ee + ah" },
    { "id": "ie", "pinyin": "ie", "type": "compound", "description": "like '**ye**s'" },
    { "id": "ua", "pinyin": "ua", "type": "compound", "description": "oo + ah, like '**wa**h'" },
    { "id": "uo", "pinyin": "uo", "type": "compound", "description": "oo + oh" },
    {
      "id": "üe",
      "pinyin": "üe",
      "type": "compound",
      "description": "ü + eh, like '**y**et' with pursed lips"
    },
    {
      "id": "iao",
      "pinyin": "iao",
      "type": "compound",
      "description": "ee + ah + oh, like '**yow**'"
    },
    { "id": "iu", "pinyin": "iu", "type": "compound", "description": "ee + oh, like '**yo**'" },
    { "id": "ui", "pinyin": "ui", "type": "compound", "description": "oo + ay, like '**way**'" },
    { "id": "uai", "pinyin": "uai", "type": "compound", "description": "oo + eye, like '**why**'" },
    { "id": "er", "pinyin": "er", "type": "compound", "description": "like '**ur**' in 'f**ur**'" },
    { "id": "an", "pinyin": "an", "type": "nasal", "description": "like '**an**'" },
    { "id": "en", "pinyin": "en", "type": "nasal", "description": "like '**en**' in '**en**tire'" },
    { "id": "in", "pinyin": "in", "type": "nasal", "description": "like '**in**'" },
    {
      "id": "un",
      "pinyin": "un",
      "type": "nasal",
      "description": "like '**un**' in '**un**der', not '**un**cle'"
    },
    { "id": "ün", "pinyin": "ün", "type": "nasal", "description": "ü + n, like '**ün**'" },
    {
      "id": "ang",
      "pinyin": "ang",
      "type": "nasal",
      "description": "like '**ong**' in 's**ong**'"
    },
    {
      "id": "eng",
      "pinyin": "eng",
      "type": "nasal",
      "description": "like '**ung**' in 's**ung**'"
    },
    { "id": "ing", "pinyin": "ing", "type": "nasal", "description": "like '**ing**'" },
    {
      "id": "ong",
      "pinyin": "ong",
      "type": "nasal",
      "description": "like '**ong**' in 's**ong**' with rounded lips"
    },
    { "id": "ian", "pinyin": "ian", "type": "nasal", "description": "like '**yen**'" },
    { "id": "uan", "pinyin": "uan", "type": "nasal", "description": "oo + an, like '**wan**'" },
    {
      "id": "üan",
      "pinyin": "üan",
      "type": "nasal",
      "description": "ü + an, like '**y** + **an**' with pursed lips"
    },
    {
      "id": "iang",
      "pinyin": "iang",
      "type": "nasal",
      "description": "ee + ang, like '**young**'"
    },
    { "id": "uang", "pinyin": "uang", "type": "nasal", "description": "oo + ang, like '**wong**'" },
    { "id": "iong", "pinyin": "iong", "type": "nasal", "description": "ee + ong, like '**yong**'" },
    { "id": "uen", "pinyin": "uen", "type": "nasal", "description": "oo + en, like '**wen**'" },
    { "id": "ueng", "pinyin": "ueng", "type": "nasal", "description": "oo + eng, like '**weng**'" }
  ],
  "combinations": [
    { "initial": "b", "final": "a", "tones": ["bā", "bá", "bǎ", "bà", "ba"] },
    { "initial": "b", "final": "o", "tones": ["bō", "bó", "bǒ", "bò", "bo"] },
    { "initial": "b", "final": "i", "tones": ["bī", "bí", "bǐ", "bì", "bi"] },
    { "initial": "b", "final": "u", "tones": ["bū", "bú", "bǔ", "bù", "bu"] },
    { "initial": "b", "final": "ai", "tones": ["bāi", "bái", "bǎi", "bài", "bai"] },
    { "initial": "b", "final": "ei", "tones": ["bēi", "béi", "běi", "bèi", "bei"] },
    { "initial": "b", "final": "ao", "tones": ["bāo", "báo", "bǎo", "bào", "bao"] },
    { "initial": "b", "final": "an", "tones": ["bān", "bán", "bǎn", "bàn", "ban"] },
    { "initial": "b", "final": "en", "tones": ["bēn", "bén", "běn", "bèn", "ben"] },
    { "initial": "b", "final": "ang", "tones": ["bāng", "báng", "bǎng", "bàng", "bang"] },
    { "initial": "b", "final": "eng", "tones": ["bēng", "béng", "běng", "bèng", "beng"] },
    { "initial": "b", "final": "ian", "tones": ["biān", "bián", "biǎn", "biàn", "bian"] },
    { "initial": "b", "final": "in", "tones": ["bīn", "bín", "bǐn", "bìn", "bin"] },
    { "initial": "b", "final": "ing", "tones": ["bīng", "bíng", "bǐng", "bìng", "bing"] },
    { "initial": "b", "final": "ie", "tones": ["biē", "bié", "biě", "biè", "bie"] },
    { "initial": "p", "final": "a", "tones": ["pā", "pá", "pǎ", "pà", "pa"] },
    { "initial": "p", "final": "o", "tones": ["pō", "pó", "pǒ", "pò", "po"] },
    { "initial": "p", "final": "i", "tones": ["pī", "pí", "pǐ", "pì", "pi"] },
    { "initial": "p", "final": "u", "tones": ["pū", "pú", "pǔ", "pù", "pu"] },
    { "initial": "p", "final": "ai", "tones": ["pāi", "pái", "pǎi", "pài", "pai"] },
    { "initial": "p", "final": "ei", "tones": ["pēi", "péi", "pěi", "pèi", "pei"] },
    { "initial": "p", "final": "ao", "tones": ["pāo", "páo", "pǎo", "pào", "pao"] },
    { "initial": "p", "final": "ou", "tones": ["pōu", "póu", "pǒu", "pòu", "pou"] },
    { "initial": "p", "final": "an", "tones": ["pān", "pán", "pǎn", "pàn", "pan"] },
    { "initial": "p", "final": "en", "tones": ["pēn", "pén", "pěn", "pèn", "pen"] },
    { "initial": "p", "final": "ang", "tones": ["pāng", "páng", "pǎng", "pàng", "pang"] },
    { "initial": "p", "final": "eng", "tones": ["pēng", "péng", "pěng", "pèng", "peng"] },
    { "initial": "p", "final": "ian", "tones": ["piān", "pián", "piǎn", "piàn", "pian"] },
    { "initial": "p", "final": "in", "tones": ["pīn", "pín", "pǐn", "pìn", "pin"] },
    { "initial": "p", "final": "ing", "tones": ["pīng", "píng", "pǐng", "pìng", "ping"] },
    { "initial": "p", "final": "ie", "tones": ["piē", "pié", "piě", "piè", "pie"] },
    { "initial": "m", "final": "a", "tones": ["mā", "má", "mǎ", "mà", "ma"] },
    { "initial": "m", "final": "o", "tones": ["mō", "mó", "mǒ", "mò", "mo"] },
    { "initial": "m", "final": "i", "tones": ["mī", "mí", "mǐ", "mì", "mi"] },
    { "initial": "m", "final": "u", "tones": ["mū", "mú", "mǔ", "mù", "mu"] },
    { "initial": "m", "final": "ai", "tones": ["māi", "mái", "mǎi", "mài", "mai"] },
    { "initial": "m", "final": "ei", "tones": ["mēi", "méi", "měi", "mèi", "mei"] },
    { "initial": "m", "final": "ao", "tones": ["māo", "máo", "mǎo", "mào", "mao"] },
    { "initial": "m", "final": "ou", "tones": ["mōu", "móu", "mǒu", "mòu", "mou"] },
    { "initial": "m", "final": "an", "tones": ["mān", "mán", "mǎn", "màn", "man"] },
    { "initial": "m", "final": "en", "tones": ["mēn", "mén", "měn", "mèn", "men"] },
    { "initial": "m", "final": "ang", "tones": ["māng", "máng", "mǎng", "màng", "mang"] },
    { "initial": "m", "final": "eng", "tones": ["mēng", "méng", "měng", "mèng", "meng"] },
    { "initial": "m", "final": "ian", "tones": ["miān", "mián", "miǎn", "miàn", "mian"] },
    { "initial": "m", "final": "in", "tones": ["mīn", "mín", "mǐn", "mìn", "min"] },
    { "initial": "m", "final": "ing", "tones": ["mīng", "míng", "mǐng", "mìng", "ming"] },
    { "initial": "m", "final": "ie", "tones": ["miē", "mié", "miě", "miè", "mie"] },
    { "initial": "m", "final": "iu", "tones": ["miū", "miú", "miǔ", "miù", "miu"] },
    { "initial": "f", "final": "a", "tones": ["fā", "fá", "fǎ", "fà", "fa"] },
    { "initial": "f", "final": "o", "tones": ["fō", "fó", "fǒ", "fò", "fo"] },
    { "initial": "f", "final": "u", "tones": ["fū", "fú", "fǔ", "fù", "fu"] },
    { "initial": "f", "final": "ei", "tones": ["fēi", "féi", "fěi", "fèi", "fei"] },
    { "initial": "f", "final": "ou", "tones": ["fōu", "fóu", "fǒu", "fòu", "fou"] },
    { "initial": "f", "final": "an", "tones": ["fān", "fán", "fǎn", "fàn", "fan"] },
    { "initial": "f", "final": "en", "tones": ["fēn", "fén", "fěn", "fèn", "fen"] },
    { "initial": "f", "final": "ang", "tones": ["fāng", "fáng", "fǎng", "fàng", "fang"] },
    { "initial": "f", "final": "eng", "tones": ["fēng", "féng", "fěng", "fèng", "feng"] },
    { "initial": "d", "final": "a", "tones": ["dā", "dá", "dǎ", "dà", "da"] },
    { "initial": "d", "final": "e", "tones": ["dē", "dé", "dě", "dè", "de"] },
    { "initial": "d", "final": "i", "tones": ["dī", "dí", "dǐ", "dì", "di"] },
    { "initial": "d", "final": "u", "tones": ["dū", "dú", "dǔ", "dù", "du"] },
    { "initial": "d", "final": "ai", "tones": ["dāi", "dái", "dǎi", "dài", "dai"] },
    { "initial": "d", "final": "ei", "tones": ["dēi", "déi", "děi", "dèi", "dei"] },
    { "initial": "d", "final": "ao", "tones": ["dāo", "dáo", "dǎo", "dào", "dao"] },
    { "initial": "d", "final": "ou", "tones": ["dōu", "dóu", "dǒu", "dòu", "dou"] },
    { "initial": "d", "final": "an", "tones": ["dān", "dán", "dǎn", "dàn", "dan"] },
    { "initial": "d", "final": "en", "tones": ["dēn", "dén", "dě", "dèn", "den"] },
    { "initial": "d", "final": "ang", "tones": ["dāng", "dáng", "dǎng", "dàng", "dang"] },
    { "initial": "d", "final": "eng", "tones": ["dēng", "déng", "děng", "dèng", "deng"] },
    { "initial": "d", "final": "ong", "tones": ["dōng", "dóng", "dǒng", "dòng", "dong"] },
    { "initial": "d", "final": "ian", "tones": ["diān", "dián", "diǎn", "diàn", "dian"] },
    { "initial": "d", "final": "ing", "tones": ["dīng", "díng", "dǐng", "dìng", "ding"] },
    { "initial": "d", "final": "iu", "tones": ["diū", "diú", "diǔ", "diù", "diu"] },
    { "initial": "d", "final": "ie", "tones": ["diē", "dié", "diě", "diè", "die"] },
    { "initial": "d", "final": "ua", "tones": ["duā", "duá", "duǎ", "duà", "dua"] },
    { "initial": "d", "final": "uo", "tones": ["duō", "duó", "duǒ", "duò", "duo"] },
    { "initial": "d", "final": "ui", "tones": ["duī", "duí", "duǐ", "duì", "dui"] },
    { "initial": "d", "final": "uan", "tones": ["duān", "duán", "duǎn", "duàn", "duan"] },
    { "initial": "d", "final": "un", "tones": ["dūn", "dún", "dǔn", "dùn", "dun"] },
    { "initial": "t", "final": "a", "tones": ["tā", "tá", "tǎ", "tà", "ta"] },
    { "initial": "t", "final": "e", "tones": ["tē", "té", "tě", "tè", "te"] },
    { "initial": "t", "final": "i", "tones": ["tī", "tí", "tǐ", "tì", "ti"] },
    { "initial": "t", "final": "u", "tones": ["tū", "tú", "tǔ", "tù", "tu"] },
    { "initial": "t", "final": "ai", "tones": ["tāi", "tái", "tǎi", "tài", "tai"] },
    { "initial": "t", "final": "ei", "tones": ["tēi", "téi", "těi", "tèi", "tei"] },
    { "initial": "t", "final": "ao", "tones": ["tāo", "táo", "tǎo", "tào", "tao"] },
    { "initial": "t", "final": "ou", "tones": ["tōu", "tóu", "tǒu", "tòu", "tou"] },
    { "initial": "t", "final": "an", "tones": ["tān", "tán", "tǎn", "tàn", "tan"] },
    { "initial": "t", "final": "ang", "tones": ["tāng", "táng", "tǎng", "tàng", "tang"] },
    { "initial": "t", "final": "eng", "tones": ["tēng", "téng", "těng", "tèng", "teng"] },
    { "initial": "t", "final": "ong", "tones": ["tōng", "tóng", "tǒng", "tòng", "tong"] },
    { "initial": "t", "final": "ian", "tones": ["tiān", "tián", "tiǎn", "tiàn", "tian"] },
    { "initial": "t", "final": "ing", "tones": ["tīng", "tíng", "tǐng", "tìng", "ting"] },
    { "initial": "t", "final": "ie", "tones": ["tiē", "tié", "tiě", "tiè", "tie"] },
    { "initial": "t", "final": "iao", "tones": ["tiāo", "tiáo", "tiǎo", "tiào", "tiao"] },
    { "initial": "t", "final": "uo", "tones": ["tuō", "tuó", "tuǒ", "tuò", "tuo"] },
    { "initial": "t", "final": "ui", "tones": ["tuī", "tuí", "tuǐ", "tuì", "tui"] },
    { "initial": "t", "final": "uan", "tones": ["tuān", "tuán", "tuǎn", "tuàn", "tuan"] },
    { "initial": "t", "final": "un", "tones": ["tūn", "tún", "tǔn", "tùn", "tun"] },
    { "initial": "n", "final": "a", "tones": ["nā", "ná", "nǎ", "nà", "na"] },
    { "initial": "n", "final": "e", "tones": ["nē", "né", "ně", "nè", "ne"] },
    { "initial": "n", "final": "i", "tones": ["nī", "ní", "nǐ", "nì", "ni"] },
    { "initial": "n", "final": "u", "tones": ["nū", "nú", "nǔ", "nù", "nu"] },
    { "initial": "n", "final": "ü", "tones": ["nǖ", "nǘ", "nǚ", "nǜ", "nü"] },
    { "initial": "n", "final": "ai", "tones": ["nāi", "nái", "nǎi", "nài", "nai"] },
    { "initial": "n", "final": "ei", "tones": ["nēi", "néi", "něi", "nèi", "nei"] },
    { "initial": "n", "final": "ao", "tones": ["nāo", "náo", "nǎo", "nào", "nao"] },
    { "initial": "n", "final": "ou", "tones": ["nōu", "nóu", "nǒu", "nòu", "nou"] },
    { "initial": "n", "final": "an", "tones": ["nān", "nán", "nǎn", "nàn", "nan"] },
    { "initial": "n", "final": "en", "tones": ["nēn", "nén", "něn", "nèn", "nen"] },
    { "initial": "n", "final": "ang", "tones": ["nāng", "náng", "nǎng", "nàng", "nang"] },
    { "initial": "n", "final": "eng", "tones": ["nēng", "néng", "něng", "nèng", "neng"] },
    { "initial": "n", "final": "ong", "tones": ["nōng", "nóng", "nǒng", "nòng", "nong"] },
    { "initial": "n", "final": "ian", "tones": ["niān", "nián", "niǎn", "niàn", "nian"] },
    { "initial": "n", "final": "in", "tones": ["nīn", "nín", "nǐn", "nìn", "nin"] },
    { "initial": "n", "final": "iang", "tones": ["niāng", "niáng", "niǎng", "niàng", "niang"] },
    { "initial": "n", "final": "ing", "tones": ["nīng", "níng", "nǐng", "nìng", "ning"] },
    { "initial": "n", "final": "ie", "tones": ["niē", "nié", "niě", "niè", "nie"] },
    { "initial": "n", "final": "iao", "tones": ["niāo", "niáo", "niǎo", "niào", "niao"] },
    { "initial": "n", "final": "iu", "tones": ["niū", "niú", "niǔ", "niù", "niu"] },
    { "initial": "n", "final": "uo", "tones": ["nuō", "nuó", "nuǒ", "nuò", "nuo"] },
    { "initial": "n", "final": "uan", "tones": ["nuān", "nuán", "nuǎn", "nuàn", "nuan"] },
    { "initial": "n", "final": "un", "tones": ["nūn", "nún", "nǔn", "nùn", "nun"] },
    { "initial": "l", "final": "a", "tones": ["lā", "lá", "lǎ", "là", "la"] },
    { "initial": "l", "final": "o", "tones": ["lō", "ló", "lǒ", "lò", "lo"] },
    { "initial": "l", "final": "e", "tones": ["lē", "lé", "lě", "lè", "le"] },
    { "initial": "l", "final": "i", "tones": ["lī", "lí", "lǐ", "lì", "li"] },
    { "initial": "l", "final": "u", "tones": ["lū", "lú", "lǔ", "lù", "lu"] },
    { "initial": "l", "final": "ü", "tones": ["lǖ", "lǘ", "lǚ", "lǜ", "lü"] },
    { "initial": "l", "final": "ai", "tones": ["lāi", "lái", "lǎi", "lài", "lai"] },
    { "initial": "l", "final": "ei", "tones": ["lēi", "léi", "lěi", "lèi", "lei"] },
    { "initial": "l", "final": "ao", "tones": ["lāo", "láo", "lǎo", "lào", "lao"] },
    { "initial": "l", "final": "ou", "tones": ["lōu", "lóu", "lǒu", "lòu", "lou"] },
    { "initial": "l", "final": "an", "tones": ["lān", "lán", "lǎn", "làn", "lan"] },
    { "initial": "l", "final": "en", "tones": ["līn", "lín", "lǐn", "lìn", "lin"] },
    { "initial": "l", "final": "ang", "tones": ["lāng", "láng", "lǎng", "làng", "lang"] },
    { "initial": "l", "final": "eng", "tones": ["lēng", "léng", "lěng", "lèng", "leng"] },
    { "initial": "l", "final": "ong", "tones": ["lōng", "lóng", "lǒng", "lòng", "long"] },
    { "initial": "l", "final": "ian", "tones": ["liān", "lián", "liǎn", "liàn", "lian"] },
    { "initial": "l", "final": "in", "tones": ["līn", "lín", "lǐn", "lìn", "lin"] },
    { "initial": "l", "final": "iang", "tones": ["liāng", "liáng", "liǎng", "liàng", "liang"] },
    { "initial": "l", "final": "ing", "tones": ["līng", "líng", "lǐng", "lìng", "ling"] },
    { "initial": "l", "final": "ie", "tones": ["liē", "lié", "liě", "liè", "lie"] },
    { "initial": "l", "final": "iao", "tones": ["liāo", "liáo", "liǎo", "liào", "liao"] },
    { "initial": "l", "final": "iu", "tones": ["liū", "liú", "liǔ", "liù", "liu"] },
    { "initial": "l", "final": "uo", "tones": ["luō", "luó", "luǒ", "luò", "luo"] },
    { "initial": "l", "final": "ui", "tones": ["luī", "luí", "luǐ", "luì", "lui"] },
    { "initial": "l", "final": "uan", "tones": ["luān", "luán", "luǎn", "luàn", "luan"] },
    { "initial": "l", "final": "un", "tones": ["lūn", "lún", "lǔn", "lùn", "lun"] },
    { "initial": "l", "final": "üe", "tones": ["lüē", "lüé", "lüě", "lüè", "lüe"] },
    { "initial": "g", "final": "a", "tones": ["gā", "gá", "gǎ", "gà", "ga"] },
    { "initial": "g", "final": "e", "tones": ["gē", "gé", "gě", "gè", "ge"] },
    { "initial": "g", "final": "u", "tones": ["gū", "gú", "gǔ", "gù", "gu"] },
    { "initial": "g", "final": "ai", "tones": ["gāi", "gái", "gǎi", "gài", "gai"] },
    { "initial": "g", "final": "ei", "tones": ["gēi", "géi", "gěi", "gèi", "gei"] },
    { "initial": "g", "final": "ao", "tones": ["gāo", "gáo", "gǎo", "gào", "gao"] },
    { "initial": "g", "final": "ou", "tones": ["gōu", "góu", "gǒu", "gòu", "gou"] },
    { "initial": "g", "final": "an", "tones": ["gān", "gán", "gǎn", "gàn", "gan"] },
    { "initial": "g", "final": "en", "tones": ["gēn", "gén", "gěn", "gèn", "gen"] },
    { "initial": "g", "final": "ang", "tones": ["gāng", "gáng", "gǎng", "gàng", "gang"] },
    { "initial": "g", "final": "eng", "tones": ["gēng", "géng", "gěng", "gèng", "geng"] },
    { "initial": "g", "final": "ong", "tones": ["gōng", "góng", "gǒng", "gòng", "gong"] },
    { "initial": "g", "final": "ua", "tones": ["guā", "guá", "guǎ", "guà", "gua"] },
    { "initial": "g", "final": "uo", "tones": ["guō", "guó", "guǒ", "guò", "guo"] },
    { "initial": "g", "final": "uai", "tones": ["guāi", "guái", "guǎi", "guài", "guai"] },
    { "initial": "g", "final": "ui", "tones": ["guī", "guí", "guǐ", "guì", "gui"] },
    { "initial": "g", "final": "uan", "tones": ["guān", "guán", "guǎn", "guàn", "guan"] },
    { "initial": "g", "final": "un", "tones": ["gūn", "gún", "gǔn", "gùn", "gun"] },
    { "initial": "g", "final": "uang", "tones": ["guāng", "guáng", "guǎng", "guàng", "guang"] },
    { "initial": "k", "final": "a", "tones": ["kā", "ká", "kǎ", "kà", "ka"] },
    { "initial": "k", "final": "e", "tones": ["kē", "ké", "kě", "kè", "ke"] },
    { "initial": "k", "final": "u", "tones": ["kū", "kú", "kǔ", "kù", "ku"] },
    { "initial": "k", "final": "ai", "tones": ["kāi", "kái", "kǎi", "kài", "kai"] },
    { "initial": "k", "final": "ei", "tones": ["kēi", "kéi", "kěi", "kèi", "kei"] },
    { "initial": "k", "final": "ao", "tones": ["kāo", "káo", "kǎo", "kào", "kao"] },
    { "initial": "k", "final": "ou", "tones": ["kōu", "kóu", "kǒu", "kòu", "kou"] },
    { "initial": "k", "final": "an", "tones": ["kān", "kán", "kǎn", "kàn", "kan"] },
    { "initial": "k", "final": "en", "tones": ["kēn", "kén", "kěn", "kèn", "ken"] },
    { "initial": "k", "final": "ang", "tones": ["kāng", "káng", "kǎng", "kàng", "kang"] },
    { "initial": "k", "final": "eng", "tones": ["kēng", "kéng", "kěng", "kèng", "keng"] },
    { "initial": "k", "final": "ong", "tones": ["kōng", "kóng", "kǒng", "kòng", "kong"] },
    { "initial": "k", "final": "ua", "tones": ["kuā", "kuá", "kuǎ", "kuà", "kua"] },
    { "initial": "k", "final": "uo", "tones": ["kuō", "kuó", "kuǒ", "kuò", "kuo"] },
    { "initial": "k", "final": "uai", "tones": ["kuāi", "kuái", "kuǎi", "kuài", "kuai"] },
    { "initial": "k", "final": "ui", "tones": ["kuī", "kuí", "kuǐ", "kuì", "kui"] },
    { "initial": "k", "final": "uan", "tones": ["kuān", "kuán", "kuǎn", "kuàn", "kuan"] },
    { "initial": "k", "final": "un", "tones": ["kūn", "kún", "kǔn", "kùn", "kun"] },
    { "initial": "k", "final": "uang", "tones": ["kuāng", "kuáng", "kuǎng", "kuàng", "kuang"] },
    { "initial": "h", "final": "a", "tones": ["hā", "há", "hǎ", "hà", "ha"] },
    { "initial": "h", "final": "e", "tones": ["hē", "hé", "hě", "hè", "he"] },
    { "initial": "h", "final": "u", "tones": ["hū", "hú", "hǔ", "hù", "hu"] },
    { "initial": "h", "final": "ai", "tones": ["hāi", "hái", "hǎi", "hài", "hai"] },
    { "initial": "h", "final": "ei", "tones": ["hēi", "héi", "hěi", "hèi", "hei"] },
    { "initial": "h", "final": "ao", "tones": ["hāo", "háo", "hǎo", "hào", "hao"] },
    { "initial": "h", "final": "ou", "tones": ["hōu", "hóu", "hǒu", "hòu", "hou"] },
    { "initial": "h", "final": "an", "tones": ["hān", "hán", "hǎn", "hàn", "han"] },
    { "initial": "h", "final": "en", "tones": ["hēn", "hén", "hěn", "hèn", "hen"] },
    { "initial": "h", "final": "ang", "tones": ["hāng", "háng", "hǎng", "hàng", "hang"] },
    { "initial": "h", "final": "eng", "tones": ["hēng", "héng", "hěng", "hèng", "heng"] },
    { "initial": "h", "final": "ong", "tones": ["hōng", "hóng", "hǒng", "hòng", "hong"] },
    { "initial": "h", "final": "ua", "tones": ["huā", "huá", "huǎ", "huà", "hua"] },
    { "initial": "h", "final": "uo", "tones": ["huō", "huó", "huǒ", "huò", "huo"] },
    { "initial": "h", "final": "uai", "tones": ["huāi", "huái", "huǎi", "huài", "huai"] },
    { "initial": "h", "final": "ui", "tones": ["huī", "huí", "huǐ", "huì", "hui"] },
    { "initial": "h", "final": "uan", "tones": ["huān", "huán", "huǎn", "huàn", "huan"] },
    { "initial": "h", "final": "un", "tones": ["hūn", "hún", "hǔn", "hùn", "hun"] },
    { "initial": "h", "final": "uang", "tones": ["huāng", "huáng", "huǎng", "huàng", "huang"] },
    { "initial": "j", "final": "i", "tones": ["jī", "jí", "jǐ", "jì", "ji"] },
    { "initial": "j", "final": "ia", "tones": ["jiā", "jiá", "jiǎ", "jià", "jia"] },
    { "initial": "j", "final": "ie", "tones": ["jiē", "jié", "jiě", "jiè", "jie"] },
    { "initial": "j", "final": "iao", "tones": ["jiāo", "jiáo", "jiǎo", "jiào", "jiao"] },
    { "initial": "j", "final": "iu", "tones": ["jiū", "jiú", "jiǔ", "jiù", "jiu"] },
    { "initial": "j", "final": "ian", "tones": ["jiān", "jián", "jiǎn", "jiàn", "jian"] },
    { "initial": "j", "final": "in", "tones": ["jīn", "jín", "jǐn", "jìn", "jin"] },
    { "initial": "j", "final": "iang", "tones": ["jiāng", "jiáng", "jiǎng", "jiàng", "jiang"] },
    { "initial": "j", "final": "ing", "tones": ["jīng", "jíng", "jǐng", "jìng", "jing"] },
    { "initial": "j", "final": "iong", "tones": ["jiōng", "jióng", "jiǒng", "jiòng", "jiong"] },
    { "initial": "j", "final": "u", "tones": ["jū", "jú", "jǔ", "jù", "ju"] },
    { "initial": "j", "final": "ue", "tones": ["juē", "jué", "juě", "juè", "jue"] },
    { "initial": "j", "final": "uan", "tones": ["juān", "juán", "juǎn", "juàn", "juan"] },
    { "initial": "j", "final": "un", "tones": ["jūn", "jún", "jǔn", "jùn", "jun"] },
    { "initial": "q", "final": "i", "tones": ["qī", "qí", "qǐ", "qì", "qi"] },
    { "initial": "q", "final": "ia", "tones": ["qiā", "qiá", "qiǎ", "qià", "qia"] },
    { "initial": "q", "final": "ie", "tones": ["qiē", "qié", "qiě", "qiè", "qie"] },
    { "initial": "q", "final": "iao", "tones": ["qiāo", "qiáo", "qiǎo", "qiào", "qiao"] },
    { "initial": "q", "final": "iu", "tones": ["qiū", "qiú", "qiǔ", "qiù", "qiu"] },
    { "initial": "q", "final": "ian", "tones": ["qiān", "qián", "qiǎn", "qiàn", "qian"] },
    { "initial": "q", "final": "in", "tones": ["qīn", "qín", "qǐn", "qìn", "qin"] },
    { "initial": "q", "final": "iang", "tones": ["qiāng", "qiáng", "qiǎng", "qiàng", "qiang"] },
    { "initial": "q", "final": "ing", "tones": ["qīng", "qíng", "qǐng", "qìng", "qing"] },
    { "initial": "q", "final": "iong", "tones": ["qiōng", "qióng", "qiǒng", "qiòng", "qiong"] },
    { "initial": "q", "final": "u", "tones": ["qū", "qú", "qǔ", "qù", "qu"] },
    { "initial": "q", "final": "ue", "tones": ["quē", "qué", "quě", "què", "que"] },
    { "initial": "q", "final": "uan", "tones": ["quān", "quán", "quǎn", "quàn", "quan"] },
    { "initial": "q", "final": "un", "tones": ["qūn", "qún", "qǔn", "qùn", "qun"] },
    { "initial": "x", "final": "i", "tones": ["xī", "xí", "xǐ", "xì", "xi"] },
    { "initial": "x", "final": "ia", "tones": ["xiā", "xiá", "xiǎ", "xià", "xia"] },
    { "initial": "x", "final": "ie", "tones": ["xiē", "xié", "xiě", "xiè", "xie"] },
    { "initial": "x", "final": "iao", "tones": ["xiāo", "xiáo", "xiǎo", "xiào", "xiao"] },
    { "initial": "x", "final": "iu", "tones": ["xiū", "xiú", "xiǔ", "xiù", "xiu"] },
    { "initial": "x", "final": "ian", "tones": ["xiān", "xián", "xiǎn", "xiàn", "xian"] },
    { "initial": "x", "final": "in", "tones": ["xīn", "xín", "xǐn", "xìn", "xin"] },
    { "initial": "x", "final": "iang", "tones": ["xiāng", "xiáng", "xiǎng", "xiàng", "xiang"] },
    { "initial": "x", "final": "ing", "tones": ["xīng", "xíng", "xǐng", "xìng", "xing"] },
    { "initial": "x", "final": "iong", "tones": ["xiōng", "xióng", "xiǒng", "xiòng", "xiong"] },
    { "initial": "x", "final": "u", "tones": ["xū", "xú", "xǔ", "xù", "xu"] },
    { "initial": "x", "final": "ue", "tones": ["xuē", "xué", "xuě", "xuè", "xue"] },
    { "initial": "x", "final": "uan", "tones": ["xuān", "xuán", "xuǎn", "xuàn", "xuan"] },
    { "initial": "x", "final": "un", "tones": ["xūn", "xún", "xǔn", "xùn", "xun"] },
    { "initial": "zh", "final": "a", "tones": ["zhā", "zhá", "zhǎ", "zhà", "zha"] },
    { "initial": "zh", "final": "e", "tones": ["zhē", "zhé", "zhě", "zhè", "zhe"] },
    { "initial": "zh", "final": "i", "tones": ["zhī", "zhí", "zhǐ", "zhì", "zhi"] },
    { "initial": "zh", "final": "u", "tones": ["zhū", "zhú", "zhǔ", "zhù", "zhu"] },
    { "initial": "zh", "final": "ai", "tones": ["zhāi", "zhái", "zhǎi", "zhài", "zhai"] },
    { "initial": "zh", "final": "ei", "tones": ["zhēi", "zhéi", "zhěi", "zhèi", "zhei"] },
    { "initial": "zh", "final": "ao", "tones": ["zhāo", "zháo", "zhǎo", "zhào", "zhao"] },
    { "initial": "zh", "final": "ou", "tones": ["zhōu", "zhóu", "zhǒu", "zhòu", "zhou"] },
    { "initial": "zh", "final": "an", "tones": ["zhān", "zhán", "zhǎn", "zhàn", "zhan"] },
    { "initial": "zh", "final": "en", "tones": ["zhēn", "zhén", "zhěn", "zhèn", "zhen"] },
    { "initial": "zh", "final": "ang", "tones": ["zhāng", "zháng", "zhǎng", "zhàng", "zhang"] },
    { "initial": "zh", "final": "eng", "tones": ["zhēng", "zhéng", "zhěng", "zhèng", "zheng"] },
    { "initial": "zh", "final": "ong", "tones": ["zhōng", "zhóng", "zhǒng", "zhòng", "zhong"] },
    { "initial": "zh", "final": "ua", "tones": ["zhuā", "zhuá", "zhuǎ", "zhuà", "zhua"] },
    { "initial": "zh", "final": "uo", "tones": ["zhuō", "zhuó", "zhuǒ", "zhuò", "zhuo"] },
    { "initial": "zh", "final": "uai", "tones": ["zhuāi", "zhuái", "zhuǎi", "zhuài", "zhuai"] },
    { "initial": "zh", "final": "ui", "tones": ["zhuī", "zhuí", "zhuǐ", "zhuì", "zhui"] },
    { "initial": "zh", "final": "uan", "tones": ["zhuān", "zhuán", "zhuǎn", "zhuàn", "zhuan"] },
    { "initial": "zh", "final": "un", "tones": ["zhūn", "zhún", "zhǔn", "zhùn", "zhun"] },
    {
      "initial": "zh",
      "final": "uang",
      "tones": ["zhuāng", "zhuáng", "zhuǎng", "zhuàng", "zhuang"]
    },
    { "initial": "ch", "final": "a", "tones": ["chā", "chá", "chǎ", "chà", "cha"] },
    { "initial": "ch", "final": "e", "tones": ["chē", "ché", "chě", "chè", "che"] },
    { "initial": "ch", "final": "i", "tones": ["chī", "chí", "chǐ", "chì", "chi"] },
    { "initial": "ch", "final": "u", "tones": ["chū", "chú", "chǔ", "chù", "chu"] },
    { "initial": "ch", "final": "ai", "tones": ["chāi", "chái", "chǎi", "chài", "chai"] },
    { "initial": "ch", "final": "ao", "tones": ["chāo", "cháo", "chǎo", "chào", "chao"] },
    { "initial": "ch", "final": "ou", "tones": ["chōu", "chóu", "chǒu", "chòu", "chou"] },
    { "initial": "ch", "final": "an", "tones": ["chān", "chán", "chǎn", "chàn", "chan"] },
    { "initial": "ch", "final": "en", "tones": ["chēn", "chén", "chěn", "chèn", "chen"] },
    { "initial": "ch", "final": "ang", "tones": ["chāng", "cháng", "chǎng", "chàng", "chang"] },
    { "initial": "ch", "final": "eng", "tones": ["chēng", "chéng", "chěng", "chèng", "cheng"] },
    { "initial": "ch", "final": "ong", "tones": ["chōng", "chóng", "chǒng", "chòng", "chong"] },
    { "initial": "ch", "final": "uo", "tones": ["chuō", "chuó", "chuǒ", "chuò", "chuo"] },
    { "initial": "ch", "final": "uai", "tones": ["chuāi", "chuái", "chuǎi", "chuài", "chuai"] },
    { "initial": "ch", "final": "ui", "tones": ["chuī", "chuí", "chuǐ", "chuì", "chui"] },
    { "initial": "ch", "final": "uan", "tones": ["chuān", "chuán", "chuǎn", "chuàn", "chuan"] },
    { "initial": "ch", "final": "un", "tones": ["chūn", "chún", "chǔn", "chùn", "chun"] },
    {
      "initial": "ch",
      "final": "uang",
      "tones": ["chuāng", "chuáng", "chuǎng", "chuàng", "chuang"]
    },
    { "initial": "sh", "final": "a", "tones": ["shā", "shá", "shǎ", "shà", "sha"] },
    { "initial": "sh", "final": "e", "tones": ["shē", "shé", "shě", "shè", "she"] },
    { "initial": "sh", "final": "i", "tones": ["shī", "shí", "shǐ", "shì", "shi"] },
    { "initial": "sh", "final": "u", "tones": ["shū", "shú", "shǔ", "shù", "shu"] },
    { "initial": "sh", "final": "ai", "tones": ["shāi", "shái", "shǎi", "shài", "shai"] },
    { "initial": "sh", "final": "ei", "tones": ["shēi", "shéi", "shěi", "shèi", "shei"] },
    { "initial": "sh", "final": "ao", "tones": ["shāo", "sháo", "shǎo", "shào", "shao"] },
    { "initial": "sh", "final": "ou", "tones": ["shōu", "shóu", "shǒu", "shòu", "shou"] },
    { "initial": "sh", "final": "an", "tones": ["shān", "shán", "shǎn", "shàn", "shan"] },
    { "initial": "sh", "final": "en", "tones": ["shēn", "shén", "shěn", "shèn", "shen"] },
    { "initial": "sh", "final": "ang", "tones": ["shāng", "sháng", "shǎng", "shàng", "shang"] },
    { "initial": "sh", "final": "eng", "tones": ["shēng", "shéng", "shěng", "shèng", "sheng"] },
    { "initial": "sh", "final": "ua", "tones": ["shuā", "shuá", "shuǎ", "shuà", "shua"] },
    { "initial": "sh", "final": "uo", "tones": ["shuō", "shuó", "shuǒ", "shuò", "shuo"] },
    { "initial": "sh", "final": "uai", "tones": ["shuāi", "shuái", "shuǎi", "shuài", "shuai"] },
    { "initial": "sh", "final": "ui", "tones": ["shuī", "shuí", "shuǐ", "shuì", "shui"] },
    { "initial": "sh", "final": "uan", "tones": ["shuān", "shuán", "shuǎn", "shuàn", "shuan"] },
    { "initial": "sh", "final": "un", "tones": ["shūn", "shún", "shǔn", "shùn", "shun"] },
    {
      "initial": "sh",
      "final": "uang",
      "tones": ["shuāng", "shuáng", "shuǎng", "shuàng", "shuang"]
    },
    { "initial": "r", "final": "e", "tones": ["rē", "ré", "rě", "rè", "re"] },
    { "initial": "r", "final": "i", "tones": ["rī", "rí", "rǐ", "rì", "ri"] },
    { "initial": "r", "final": "u", "tones": ["rū", "rú", "rǔ", "rù", "ru"] },
    { "initial": "r", "final": "ao", "tones": ["rāo", "ráo", "rǎo", "rào", "rao"] },
    { "initial": "r", "final": "ou", "tones": ["rōu", "róu", "rǒu", "ròu", "rou"] },
    { "initial": "r", "final": "an", "tones": ["rān", "rán", "rǎn", "ràn", "ran"] },
    { "initial": "r", "final": "en", "tones": ["rēn", "rén", "rěn", "rèn", "ren"] },
    { "initial": "r", "final": "ang", "tones": ["rāng", "ráng", "rǎng", "ràng", "rang"] },
    { "initial": "r", "final": "eng", "tones": ["rēng", "réng", "rěng", "rèng", "reng"] },
    { "initial": "r", "final": "ong", "tones": ["rōng", "róng", "rǒng", "ròng", "rong"] },
    { "initial": "r", "final": "uo", "tones": ["ruō", "ruó", "ruǒ", "ruò", "ruo"] },
    { "initial": "r", "final": "ui", "tones": ["ruī", "ruí", "ruǐ", "ruì", "rui"] },
    { "initial": "r", "final": "uan", "tones": ["ruān", "ruán", "ruǎn", "ruàn", "ruan"] },
    { "initial": "r", "final": "un", "tones": ["rūn", "rún", "rǔn", "rùn", "run"] },
    { "initial": "z", "final": "a", "tones": ["zā", "zá", "zǎ", "zà", "za"] },
    { "initial": "z", "final": "e", "tones": ["zē", "zé", "zě", "zè", "ze"] },
    { "initial": "z", "final": "i", "tones": ["zī", "zí", "zǐ", "zì", "zi"] },
    { "initial": "z", "final": "u", "tones": ["zū", "zú", "zǔ", "zù", "zu"] },
    { "initial": "z", "final": "ai", "tones": ["zāi", "zái", "zǎi", "zài", "zai"] },
    { "initial": "z", "final": "ei", "tones": ["zēi", "zéi", "zěi", "zèi", "zei"] },
    { "initial": "z", "final": "ao", "tones": ["zāo", "záo", "zǎo", "zào", "zao"] },
    { "initial": "z", "final": "ou", "tones": ["zōu", "zóu", "zǒu", "zòu", "zou"] },
    { "initial": "z", "final": "an", "tones": ["zān", "zán", "zǎn", "zàn", "zan"] },
    { "initial": "z", "final": "en", "tones": ["zēn", "zén", "zěn", "zèn", "zen"] },
    { "initial": "z", "final": "ang", "tones": ["zāng", "záng", "zǎng", "zàng", "zang"] },
    { "initial": "z", "final": "eng", "tones": ["zēng", "zéng", "zěng", "zèng", "zeng"] },
    { "initial": "z", "final": "ong", "tones": ["zōng", "zóng", "zǒng", "zòng", "zong"] },
    { "initial": "z", "final": "uo", "tones": ["zuō", "zuó", "zuǒ", "zuò", "zuo"] },
    { "initial": "z", "final": "ui", "tones": ["zuī", "zuí", "zuǐ", "zuì", "zui"] },
    { "initial": "z", "final": "uan", "tones": ["zuān", "zuán", "zuǎn", "zuàn", "zuan"] },
    { "initial": "z", "final": "un", "tones": ["zūn", "zún", "zǔn", "zùn", "zun"] },
    { "initial": "c", "final": "a", "tones": ["cā", "cá", "cǎ", "cà", "ca"] },
    { "initial": "c", "final": "e", "tones": ["cē", "cé", "cě", "cè", "ce"] },
    { "initial": "c", "final": "i", "tones": ["cī", "cí", "cǐ", "cì", "ci"] },
    { "initial": "c", "final": "u", "tones": ["cū", "cú", "cǔ", "cù", "cu"] },
    { "initial": "c", "final": "ai", "tones": ["cāi", "cái", "cǎi", "cài", "cai"] },
    { "initial": "c", "final": "ei", "tones": ["cēi", "céi", "cěi", "cèi", "cei"] },
    { "initial": "c", "final": "ao", "tones": ["cāo", "cáo", "cǎo", "cào", "cao"] },
    { "initial": "c", "final": "ou", "tones": ["cōu", "cóu", "cǒu", "còu", "cou"] },
    { "initial": "c", "final": "an", "tones": ["cān", "cán", "cǎn", "càn", "can"] },
    { "initial": "c", "final": "en", "tones": ["cēn", "cén", "cěn", "cèn", "cen"] },
    { "initial": "c", "final": "ang", "tones": ["cāng", "cáng", "cǎng", "càng", "cang"] },
    { "initial": "c", "final": "eng", "tones": ["cēng", "céng", "cěng", "cèng", "ceng"] },
    { "initial": "c", "final": "ong", "tones": ["cōng", "cóng", "cǒng", "còng", "cong"] },
    { "initial": "c", "final": "uo", "tones": ["cuō", "cuó", "cuǒ", "cuò", "cuo"] },
    { "initial": "c", "final": "ui", "tones": ["cuī", "cuí", "cuǐ", "cuì", "cui"] },
    { "initial": "c", "final": "uan", "tones": ["cuān", "cuán", "cuǎn", "cuàn", "cuan"] },
    { "initial": "c", "final": "un", "tones": ["cūn", "cún", "cǔn", "cùn", "cun"] },
    { "initial": "s", "final": "a", "tones": ["sā", "sá", "sǎ", "sà", "sa"] },
    { "initial": "s", "final": "e", "tones": ["sē", "sé", "sě", "sè", "se"] },
    { "initial": "s", "final": "i", "tones": ["sī", "sí", "sǐ", "sì", "si"] },
    { "initial": "s", "final": "u", "tones": ["sū", "sú", "sǔ", "sù", "su"] },
    { "initial": "s", "final": "ai", "tones": ["sāi", "sái", "sǎi", "sài", "sai"] },
    { "initial": "s", "final": "ei", "tones": ["sēi", "séi", "sěi", "sèi", "sei"] },
    { "initial": "s", "final": "ao", "tones": ["sāo", "sáo", "sǎo", "sào", "sao"] },
    { "initial": "s", "final": "ou", "tones": ["sōu", "sóu", "sǒu", "sòu", "sou"] },
    { "initial": "s", "final": "an", "tones": ["sān", "sán", "sǎn", "sàn", "san"] },
    { "initial": "s", "final": "en", "tones": ["sēn", "sén", "sěn", "sèn", "sen"] },
    { "initial": "s", "final": "ang", "tones": ["sāng", "sáng", "sǎng", "sàng", "sang"] },
    { "initial": "s", "final": "eng", "tones": ["sēng", "séng", "sěng", "sèng", "seng"] },
    { "initial": "s", "final": "ong", "tones": ["sōng", "sóng", "sǒng", "sòng", "song"] },
    { "initial": "s", "final": "uo", "tones": ["suō", "suó", "suǒ", "suò", "suo"] },
    { "initial": "s", "final": "ui", "tones": ["suī", "suí", "suǐ", "suì", "sui"] },
    { "initial": "s", "final": "uan", "tones": ["suān", "suán", "suǎn", "suàn", "suan"] },
    { "initial": "s", "final": "un", "tones": ["sūn", "sún", "sǔn", "sùn", "sun"] }
  ],
  "toneInfo": [
    {
      "number": 1,
      "name": "First Tone",
      "mark": "ˉ",
      "pinyinExample": "mā",
      "chineseExample": "妈",
      "description": "High level",
      "contour": [4, 4.5, 5, 5, 5],
      "color": "#FF4444"
    },
    {
      "number": 2,
      "name": "Second Tone",
      "mark": "ˊ",
      "pinyinExample": "má",
      "chineseExample": "麻",
      "description": "Rising",
      "contour": [2, 2, 3, 4, 5],
      "color": "#FF8C00"
    },
    {
      "number": 3,
      "name": "Third Tone",
      "mark": "ˇ",
      "pinyinExample": "mǎ",
      "chineseExample": "马",
      "description": "Dip then rise",
      "contour": [2, 1, 0.5, 1, 3],
      "color": "#4CAF50"
    },
    {
      "number": 4,
      "name": "Fourth Tone",
      "mark": "ˋ",
      "pinyinExample": "mà",
      "chineseExample": "骂",
      "description": "Falling",
      "contour": [5, 4.5, 3, 1, 0],
      "color": "#2196F3"
    },
    {
      "number": 0,
      "name": "Neutral Tone",
      "mark": "·",
      "pinyinExample": "ma",
      "chineseExample": "吗",
      "description": "Light / unstressed",
      "contour": [2, 2, 2, 2, 2],
      "color": "#9E9E9E"
    }
  ],
  "tonePairs": [
    {
      "id": "pair-1",
      "chinese": "你好",
      "dictionaryPinyin": "nǐ hǎo",
      "spokenPinyin": "ní hǎo",
      "rule": "3rd+3rd → 2nd+3rd",
      "pattern": "3+3"
    },
    {
      "id": "pair-2",
      "chinese": "很好",
      "dictionaryPinyin": "hěn hǎo",
      "spokenPinyin": "hén hǎo",
      "rule": "3rd+3rd → 2nd+3rd",
      "pattern": "3+3"
    },
    {
      "id": "pair-3",
      "chinese": "吃饭",
      "dictionaryPinyin": "chī fàn",
      "spokenPinyin": "chī fàn",
      "rule": "1st+4th",
      "pattern": "1+4"
    },
    {
      "id": "pair-4",
      "chinese": "学校",
      "dictionaryPinyin": "xué xiào",
      "spokenPinyin": "xué xiào",
      "rule": "2nd+4th",
      "pattern": "2+4"
    },
    {
      "id": "pair-5",
      "chinese": "但是",
      "dictionaryPinyin": "dàn shì",
      "spokenPinyin": "dàn shì",
      "rule": "4th+4th",
      "pattern": "4+4"
    },
    {
      "id": "pair-6",
      "chinese": "老师",
      "dictionaryPinyin": "lǎo shī",
      "spokenPinyin": "lǎo shī",
      "rule": "3rd+1st",
      "pattern": "3+1"
    }
  ],
  "toneRules": [
    {
      "id": "rule-3rd-sandhi",
      "title": "3rd Tone Sandhi",
      "rule": "When two 3rd tones meet, the first becomes 2nd tone",
      "examples": [
        { "chinese": "你好", "dictionary": "nǐ hǎo", "spoken": "ní hǎo" },
        { "chinese": "很好", "dictionary": "hěn hǎo", "spoken": "hén hǎo" }
      ]
    },
    {
      "id": "rule-yi",
      "title": "一 (yī) Tone Change",
      "rule": "yī becomes yí before a 4th tone; yī becomes yì before 1st/2nd/3rd tone",
      "examples": [
        { "chinese": "一个", "dictionary": "yī gè", "spoken": "yí gè" },
        { "chinese": "一起", "dictionary": "yī qǐ", "spoken": "yì qǐ" }
      ]
    },
    {
      "id": "rule-bu",
      "title": "不 (bù) Tone Change",
      "rule": "bù becomes bú before a 4th tone",
      "examples": [
        { "chinese": "不是", "dictionary": "bù shì", "spoken": "bú shì" },
        { "chinese": "不对", "dictionary": "bù duì", "spoken": "bú duì" }
      ]
    }
  ]
}
